salt_bootstrap_ssh/__init__.py
salt_bootstrap_ssh-1.1.2.dist-info/LICENSE.txt
salt_bootstrap_ssh-1.1.2.dist-info/METADATA
salt_bootstrap_ssh-1.1.2.dist-info/WHEEL
salt_bootstrap_ssh-1.1.2.dist-info/entry_points.txt
salt_bootstrap_ssh-1.1.2.dist-info/top_level.txt
salt_bootstrap_ssh-1.1.2.dist-info/RECORD
