Metadata-Version: 2.1
Name: salt-bootstrap-ssh
Version: 1.1.2
Summary: BBootstrap key based SSH authentication to a Salt Master
Home-page: https://gitlab.com/davisd50/salt-bootstrap-ssh
Author: David Davis
Author-email: davisd50@gmail.com
License: MIT
Keywords: salt
Platform: UNKNOWN
Classifier: Development Status :: 4 - Beta
Classifier: Intended Audience :: Developers
Classifier: License :: OSI Approved :: MIT License
Classifier: Natural Language :: English
Classifier: Programming Language :: Python :: 3.7
Requires-Dist: setuptools
Requires-Dist: distro
Requires-Dist: paramiko
